rbstopwatch/__init__.py
rbstopwatch/extension.py
rbstopwatch/static/css/default.min.9e900d7b8fda.css
rbstopwatch/static/css/default.min.css
rbstopwatch/static/css/stopwatch.9e900d7b8fda.css
rbstopwatch/static/css/stopwatch.css
rbstopwatch/static/css/stopwatch.e5fca48e95e8.less
rbstopwatch/static/css/stopwatch.less
rbstopwatch/static/js/default.min.34dec2a34aa7.js
rbstopwatch/static/js/default.min.js
rbstopwatch/static/js/stopwatch.ecae4878a672.js
rbstopwatch/static/js/stopwatch.js
rbstopwatch/templates/rbstopwatch-review-header.html
rbstopwatch/templatetags/__init__.py
rbstopwatch/templatetags/stopwatch_tags.py
rbstopwatch-1.0.1.dist-info/DESCRIPTION.rst
rbstopwatch-1.0.1.dist-info/METADATA
rbstopwatch-1.0.1.dist-info/RECORD
rbstopwatch-1.0.1.dist-info/WHEEL
rbstopwatch-1.0.1.dist-info/entry_points.txt
rbstopwatch-1.0.1.dist-info/metadata.json
rbstopwatch-1.0.1.dist-info/top_level.txt
