Metadata-Version: 2.0
Name: rbstopwatch
Version: 1.0.1
Summary: Stopwatch extension for Review Board
Home-page: https://www.reviewboard.org/
Author: Beanbag, Inc.
Author-email: support@beanbaginc.com
License: UNKNOWN
Platform: UNKNOWN
Classifier: Development Status :: 5 - Production/Stable
Classifier: Environment :: Web Environment
Classifier: Framework :: Review Board
Classifier: Intended Audience :: Developers
Classifier: License :: OSI Approved :: MIT License
Classifier: Natural Language :: English
Classifier: Operating System :: OS Independent
Classifier: Programming Language :: Python
